.config.json
MANIFEST.in
readme.md
requirements.txt
sdbw
setup.py
bandwidth/__init__.py
sd_bandwidth.egg-info/PKG-INFO
sd_bandwidth.egg-info/SOURCES.txt
sd_bandwidth.egg-info/dependency_links.txt
sd_bandwidth.egg-info/requires.txt
sd_bandwidth.egg-info/top_level.txt