Metadata-Version: 1.0
Name: sd-bandwidth
Version: 0.15
Summary: Command line interface to get bandwidth for a device and interface
Home-page: https://github.com/serverdensity/sd-bw
Author: Jonathan Sundqvist
Author-email: jonathan@serverdensity.com
License: UNKNOWN
Keywords: monitoring,serverdensity
Platform: UNKNOWN
